progress_runner/__init__.py
progress_runner/progress_runner.py
progress_runner-0.0.3.dist-info/METADATA
progress_runner-0.0.3.dist-info/WHEEL
progress_runner-0.0.3.dist-info/entry_points.txt
progress_runner-0.0.3.dist-info/top_level.txt
progress_runner-0.0.3.dist-info/RECORD
