Metadata-Version: 2.1
Name: progress-runner
Version: 0.0.3
Summary: an ncurses process runner with progress display
Home-page: https://github.com/danroblewis/progress_runner
Author: Daniel Lewis
Author-email: daniel.robert.lewis@gmail.com
License: MIT
Platform: UNKNOWN
Classifier: License :: OSI Approved :: MIT License
Classifier: Programming Language :: Python
Classifier: Programming Language :: Python :: 3
Classifier: Programming Language :: Python :: 3.6
Classifier: Programming Language :: Python :: Implementation :: CPython
Classifier: Programming Language :: Python :: Implementation :: PyPy
Requires-Python: >=3.7.0
